abhealer/__init__.py
abhealer/__main__.py
abhealer/abhealer.py
abhealer/arecabackup.py
abhealer/pathutils.py
abhealer/templates/project.bcfg
abhealer-0.5.0.dist-info/DESCRIPTION.rst
abhealer-0.5.0.dist-info/METADATA
abhealer-0.5.0.dist-info/RECORD
abhealer-0.5.0.dist-info/WHEEL
abhealer-0.5.0.dist-info/entry_points.txt
abhealer-0.5.0.dist-info/metadata.json
abhealer-0.5.0.dist-info/top_level.txt
tests/__init__.py
tests/test_abhealer.py
