Metadata-Version: 2.0
Name: abhealer
Version: 0.5.0
Summary: abhealer
Home-page: https://github.com/starofrainnight/abhealer
Author: Hong-She Liang
Author-email: starofrainnight@gmail.com
License: Apache Software License
Keywords: abhealer
Platform: UNKNOWN
Classifier: Development Status :: 2 - Pre-Alpha
Classifier: Intended Audience :: Developers
Classifier: License :: OSI Approved :: Apache Software License
Classifier: Natural Language :: English
Classifier: Programming Language :: Python :: 3
Classifier: Programming Language :: Python :: 3.4
Classifier: Programming Language :: Python :: 3.5
Requires-Dist: arrow
Requires-Dist: click (>=6.0)
Requires-Dist: jinja2
Requires-Dist: pyyaml
Requires-Dist: whichcraft
